openeo_processes_dask/__init__.py
openeo_processes_dask/process_implementations/__init__.py
openeo_processes_dask/process_implementations/arrays.py
openeo_processes_dask/process_implementations/comparison.py
openeo_processes_dask/process_implementations/core.py
openeo_processes_dask/process_implementations/cubes/__init__.py
openeo_processes_dask/process_implementations/cubes/_filter.py
openeo_processes_dask/process_implementations/cubes/_xr_interop.py
openeo_processes_dask/process_implementations/cubes/aggregate.py
openeo_processes_dask/process_implementations/cubes/apply.py
openeo_processes_dask/process_implementations/cubes/apply_neighborhood_intertwin.py
openeo_processes_dask/process_implementations/cubes/experimental.py
openeo_processes_dask/process_implementations/cubes/general.py
openeo_processes_dask/process_implementations/cubes/geometries.py
openeo_processes_dask/process_implementations/cubes/indices.py
openeo_processes_dask/process_implementations/cubes/load.py
openeo_processes_dask/process_implementations/cubes/mask.py
openeo_processes_dask/process_implementations/cubes/mask_polygon.py
openeo_processes_dask/process_implementations/cubes/merge.py
openeo_processes_dask/process_implementations/cubes/reduce.py
openeo_processes_dask/process_implementations/cubes/resample.py
openeo_processes_dask/process_implementations/cubes/utils.py
openeo_processes_dask/process_implementations/data_model.py
openeo_processes_dask/process_implementations/dates.py
openeo_processes_dask/process_implementations/exceptions.py
openeo_processes_dask/process_implementations/experimental/__init__.py
openeo_processes_dask/process_implementations/experimental/ddmc.py
openeo_processes_dask/process_implementations/experimental/rqadeforestation.py
openeo_processes_dask/process_implementations/inspect.py
openeo_processes_dask/process_implementations/logic.py
openeo_processes_dask/process_implementations/math.py
openeo_processes_dask/process_implementations/ml/__init__.py
openeo_processes_dask-2025.9.5.dist-info/LICENSE
openeo_processes_dask-2025.9.5.dist-info/METADATA
openeo_processes_dask-2025.9.5.dist-info/WHEEL
openeo_processes_dask-2025.9.5.dist-info/RECORD
