Metadata-Version: 2.1
Name: openeo-processes-dask
Version: 2025.9.5
Summary: Python implementations of many OpenEO processes, dask-friendly by default.
Home-page: https://github.com/Open-EO/openeo-processes-dask
License: Apache 2.0
Author: Lukas Weidenholzer
Author-email: lukas.weidenholzer@eodc.eu
Maintainer: EODC Staff
Maintainer-email: support@eodc.eu
Requires-Python: >=3.10,<3.13
Classifier: Development Status :: 4 - Beta
Classifier: Intended Audience :: Developers
Classifier: License :: Other/Proprietary License
Classifier: Programming Language :: Python
Classifier: Programming Language :: Python :: 3
Classifier: Programming Language :: Python :: 3.10
Classifier: Programming Language :: Python :: 3.11
Classifier: Programming Language :: Python :: 3 :: Only
Classifier: Programming Language :: Python :: 3.12
Provides-Extra: implementations
Provides-Extra: ml
Requires-Dist: dask-geopandas (==0.4.3) ; extra == "implementations"
Requires-Dist: dask[array,dataframe,distributed] (>=2023.4.0,<2025.2.0) ; extra == "implementations"
Requires-Dist: geopandas (>=0.11.1,<1) ; extra == "implementations"
Requires-Dist: geoparquet (>=0.0.3,<0.0.4)
Requires-Dist: joblib (>=1.3.2) ; extra == "implementations"
Requires-Dist: numpy (<2.0.0)
Requires-Dist: odc-geo (>=0.4.1,<1) ; extra == "implementations"
Requires-Dist: odc-stac (>=0.3.9) ; extra == "implementations"
Requires-Dist: openeo (>=0.36.0)
Requires-Dist: openeo-pg-parser-networkx (>=2025.9) ; extra == "implementations"
Requires-Dist: pandas (>=2.0.0)
Requires-Dist: planetary_computer (>=0.5.1) ; extra == "implementations"
Requires-Dist: pyarrow (>=15.0.2,<16.0.0)
Requires-Dist: pystac (<1.12.0)
Requires-Dist: pystac_client (>=0.6.1) ; extra == "implementations"
Requires-Dist: rasterio (>=1.3.4,<2.0.0) ; extra == "implementations"
Requires-Dist: rioxarray (>=0.12.0,<1) ; extra == "implementations"
Requires-Dist: rqadeforestation (>=0.1)
Requires-Dist: scipy (>=1.11.3,<2.0.0)
Requires-Dist: stac_validator (>=3.3.1) ; extra == "implementations"
Requires-Dist: xarray (>=2022.11.0,<2025.08.01) ; extra == "implementations"
Requires-Dist: xcube-eopf (>=0.2.0)
Requires-Dist: xgboost (>=1.5.1,<2.1.4) ; extra == "ml"
Requires-Dist: xvec (==0.2.0) ; extra == "implementations"
Requires-Dist: zarr (<=2.18.7)
Project-URL: Repository, https://github.com/Open-EO/openeo-processes-dask
